CHANGELOG.txt
LICENSE.txt
README.md
setup.py
abxy/__init__.py
abxy/__main__.py
abxy/abxy_chatbot.py
abxy/chatpreter.py
abxy/cursepreter.py
abxy/help.py
abxy/lovepreter.py
abxy.egg-info/PKG-INFO
abxy.egg-info/SOURCES.txt
abxy.egg-info/dependency_links.txt
abxy.egg-info/top_level.txt