Metadata-Version: 2.1
Name: abxy
Version: 2.3.3
Summary: Abxy is a third party library for the package named inkster.
Home-page: https://pypi.org/project/abxy/
Author: AbxyPlayz
Author-email: InksterAbxyPY@protonmail.com
License: UNKNOWN
Project-URL: Discord, https://discord.gg/HUFtMsz
Keywords: abxyplayz
Platform: UNKNOWN
Classifier: Programming Language :: Python :: 3
Classifier: License :: OSI Approved :: MIT License
Classifier: Operating System :: Microsoft :: Windows :: Windows 10
Requires-Python: >=3.8
